tinyalu_ch3_verilator/rtl/three_cycle.sv
// -----------------------------------------------------------------------------
// Three-Cycle Multiplier (SystemVerilog Conversion of Ray Salemi's VHDL)
// Enhanced Version: Parameters, Enums, Modern SV, Verilator-Friendly
// PIPE_DEPTH = 3 by default (P1)
// -----------------------------------------------------------------------------

module three_cycle #(
    parameter WIDTH         = 16,
    parameter RESULT_WIDTH  = 16,
    parameter PIPE_DEPTH    = 3     // M3: parameterized pipeline depth
) (
    input  logic [WIDTH-1:0]        A,
    input  logic [WIDTH-1:0]        B,
    input  logic                    clk,
    input  logic                    reset_n,   // R1: active-low async reset
    input  logic                    start,
    output logic                    done_mult,
    output logic [RESULT_WIDTH-1:0] result_mult
);

    // -------------------------------------------------------------------------
    // Pipeline Registers
    // -------------------------------------------------------------------------
    logic [WIDTH-1:0]        a_pipe   [PIPE_DEPTH];
    logic [WIDTH-1:0]        b_pipe   [PIPE_DEPTH];
    logic [RESULT_WIDTH-1:0] mult_pipe[PIPE_DEPTH];
    logic                    done_pipe[PIPE_DEPTH];

    // -------------------------------------------------------------------------
    // Pipeline Logic
    // -------------------------------------------------------------------------
    integer i;

    always_ff @(posedge clk or negedge reset_n) begin
        if (!reset_n) begin
            for (i = 0; i < PIPE_DEPTH; i++) begin
                a_pipe[i]    <= '0;
                b_pipe[i]    <= '0;
                mult_pipe[i] <= '0;
                done_pipe[i] <= 1'b0;
            end
            result_mult <= '0;
            done_mult   <= 1'b0;
        end else begin
            // Stage 0: capture inputs
            a_pipe[0]    <= A;
            b_pipe[0]    <= B;
            mult_pipe[0] <= A * B;
            done_pipe[0] <= start;

            // Remaining pipeline stages
            for (i = 1; i < PIPE_DEPTH; i++) begin
                a_pipe[i]    <= a_pipe[i-1];
                b_pipe[i]    <= b_pipe[i-1];
                mult_pipe[i] <= mult_pipe[i-1];
                done_pipe[i] <= done_pipe[i-1];
            end

            // Final stage output
            result_mult <= mult_pipe[PIPE_DEPTH-1];
            done_mult   <= done_pipe[PIPE_DEPTH-1];
        end
    end

endmodule

tinyalu_ch3_verilator/rtl/single_cycle.sv
// -----------------------------------------------------------------------------
// Single-Cycle Add/AND/XOR (SystemVerilog Conversion of Ray Salemi's VHDL)
// Enhanced Version: Parameters, Enums, Modern SV, Verilator-Friendly
// -----------------------------------------------------------------------------

module single_cycle #(
    parameter WIDTH         = 16,
    parameter RESULT_WIDTH  = 16
) (
    input  logic [WIDTH-1:0]        A,
    input  logic [WIDTH-1:0]        B,
    input  logic                    clk,
    input  logic                    reset_n,   // R1: active-low async reset
    input  logic                    start,
    input  tinyalu_op_t             op,        // O2: enum opcodes
    output logic                    done_aax,
    output logic [RESULT_WIDTH-1:0] result_aax
);

    // -------------------------------------------------------------------------
    // Result Logic
    // -------------------------------------------------------------------------
    always_ff @(posedge clk or negedge reset_n) begin
        if (!reset_n) begin
            result_aax <= '0;
        end else if (start) begin
            case (op)
                OP_ADD: result_aax <= A + B;
                OP_AND: result_aax <= { {(RESULT_WIDTH-WIDTH){1'b0}}, (A & B) };
                OP_XOR: result_aax <= { {(RESULT_WIDTH-WIDTH){1'b0}}, (A ^ B) };
                default: /* no-op */ ;
            endcase
        end
    end

    // -------------------------------------------------------------------------
    // Done Logic
    // -------------------------------------------------------------------------
    always_ff @(posedge clk or negedge reset_n) begin
        if (!reset_n) begin
            done_aax <= 1'b0;
        end else begin
            done_aax <= (start && (op != OP_NOP));
        end
    end

endmodule

tinyalu_ch3_verilator/rtl/tinyalu.sv
// -----------------------------------------------------------------------------
// TinyALU Top-Level (SystemVerilog Conversion of Ray Salemi's VHDL)
// Enhanced Version: Parameters, Enums, Modern SV, Verilator-Friendly
// -----------------------------------------------------------------------------

module tinyalu #(
    parameter WIDTH         = 16,
    parameter RESULT_WIDTH  = 16,
    parameter PIPE_DEPTH    = 3     // M3: parameterized pipeline depth (default 3)
) (
    input  logic [WIDTH-1:0]        A,
    input  logic [WIDTH-1:0]        B,
    input  logic                    clk,
    input  logic                    reset_n,   // R1: active-low async reset
    input  logic                    start,
    input  tinyalu_op_t             op,        // O2: enum opcodes
    output logic                    done,
    output logic [RESULT_WIDTH-1:0] result
);

    // -------------------------------------------------------------------------
    // Internal signals
    // -------------------------------------------------------------------------
    logic                    start_single;
    logic                    start_mult;

    logic                    done_aax;
    logic                    done_mult;

    logic [RESULT_WIDTH-1:0] result_aax;
    logic [RESULT_WIDTH-1:0] result_mult;
    logic [RESULT_WIDTH-1:0] prev_result;
    // Functional coverage counters     
    integer cov_add, cov_and, cov_xor, cov_mul,cov_nop;

    always_ff @(posedge clk or negedge reset_n) 
        begin
            if (!reset_n) 
                begin
                    cov_add <= 0;
                    cov_and <= 0;
                    cov_xor <= 0;
                    cov_mul <= 0;
                    cov_nop <= 0;
                end 
            else if (start)     
                begin
                    case (op)
                        OP_ADD:  cov_add <= cov_add + 1;
                        OP_AND:  cov_and <= cov_and + 1;
                        OP_XOR:  cov_xor <= cov_xor + 1;
                        OP_MUL:  cov_mul <= cov_mul + 1;
                        default: cov_nop <= cov_nop + 1;
                            
                    endcase
                end
        end

    // -------------------------------------------------------------------------
    // Start Demux: route start to correct block based on op
    // -------------------------------------------------------------------------
    always_comb begin
        if (op == OP_MUL) begin
            start_single = 1'b0;
            start_mult   = start;
        end else begin
            start_single = start;
            start_mult   = 1'b0;
        end
    end

    // -------------------------------------------------------------------------
    // Result Mux
    // -------------------------------------------------------------------------
    always_comb 
        begin
            result = '0;

            case (op)
                OP_NOP:  result = prev_result;       // no-op
                OP_ADD:  result = result_aax;
                OP_AND:  result = result_aax;
                OP_XOR:  result = result_aax;
                OP_MUL:  result = result_mult;
                default: result = prev_result;
            endcase
        end

    // -------------------------------------------------------------------------
    // Done Mux
    // -------------------------------------------------------------------------
    always_comb 
        begin
            done = 1'b0;

            case (op)
                OP_NOP:  done = 1'b0;
                OP_ADD:  done = done_aax;
                OP_AND:  done = done_aax;
                OP_XOR:  done = done_aax;
                OP_MUL:  done = done_mult;
                default: done = 1'b0;
            endcase
        end

    
    

    always_ff @(posedge clk or negedge reset_n)
        if (!reset_n)
            prev_result <= '0;
        else
            prev_result <= result;

    // -------------------------------------------------------------------------
    // Instantiations
    // -------------------------------------------------------------------------
    single_cycle #(
        .WIDTH(WIDTH),
        .RESULT_WIDTH(RESULT_WIDTH)
    ) u_single_cycle (
        .A(A),
        .B(B),
        .clk(clk),
        .reset_n(reset_n),
        .start(start_single),
        .op(op),
        .done_aax(done_aax),
        .result_aax(result_aax)
    );

    three_cycle #(
        .WIDTH(WIDTH),
        .RESULT_WIDTH(RESULT_WIDTH),
        .PIPE_DEPTH(PIPE_DEPTH)
    ) u_three_cycle (
        .A(A),
        .B(B),
        .clk(clk),
        .reset_n(reset_n),
        .start(start_mult),
        .done_mult(done_mult),
        .result_mult(result_mult)
    );

endmodule

tinyalu_ch3_verilator/tinyalu.vcd
$version Generated by VerilatedVcd $end
$timescale 1ps $end
 $scope module TOP $end
  $var wire 16 9 A [15:0] $end
  $var wire 16 : B [15:0] $end
  $var wire 1 ; clk $end
  $var wire 1 < reset_n $end
  $var wire 1 = start $end
  $var wire 3 > op [2:0] $end
  $var wire 1 ? done $end
  $var wire 16 @ result [15:0] $end
  $scope module tinyalu $end
   $var wire 32 C WIDTH [31:0] $end
   $var wire 32 C RESULT_WIDTH [31:0] $end
   $var wire 32 D PIPE_DEPTH [31:0] $end
   $var wire 16 9 A [15:0] $end
   $var wire 16 : B [15:0] $end
   $var wire 1 ; clk $end
   $var wire 1 < reset_n $end
   $var wire 1 = start $end
   $var wire 3 > op [2:0] $end
   $var wire 1 ? done $end
   $var wire 16 @ result [15:0] $end
   $var wire 1 A start_single $end
   $var wire 1 B start_mult $end
   $var wire 1 " done_aax $end
   $var wire 1 # done_mult $end
   $var wire 16 $ result_aax [15:0] $end
   $var wire 16 % result_mult [15:0] $end
   $var wire 16 & prev_result [15:0] $end
   $var wire 32 ' cov_add [31:0] $end
   $var wire 32 ( cov_and [31:0] $end
   $var wire 32 ) cov_xor [31:0] $end
   $var wire 32 * cov_mul [31:0] $end
   $var wire 32 + cov_nop [31:0] $end
   $scope module u_single_cycle $end
    $var wire 32 C WIDTH [31:0] $end
    $var wire 32 C RESULT_WIDTH [31:0] $end
    $var wire 16 9 A [15:0] $end
    $var wire 16 : B [15:0] $end
    $var wire 1 ; clk $end
    $var wire 1 < reset_n $end
    $var wire 1 A start $end
    $var wire 3 > op [2:0] $end
    $var wire 1 " done_aax $end
    $var wire 16 $ result_aax [15:0] $end
   $upscope $end
   $scope module u_three_cycle $end
    $var wire 32 C WIDTH [31:0] $end
    $var wire 32 C RESULT_WIDTH [31:0] $end
    $var wire 32 D PIPE_DEPTH [31:0] $end
    $var wire 16 9 A [15:0] $end
    $var wire 16 : B [15:0] $end
    $var wire 1 ; clk $end
    $var wire 1 < reset_n $end
    $var wire 1 B start $end
    $var wire 1 # done_mult $end
    $var wire 16 % result_mult [15:0] $end
    $var wire 16 , a_pipe[0] [15:0] $end
    $var wire 16 - a_pipe[1] [15:0] $end
    $var wire 16 . a_pipe[2] [15:0] $end
    $var wire 16 / b_pipe[0] [15:0] $end
    $var wire 16 0 b_pipe[1] [15:0] $end
    $var wire 16 1 b_pipe[2] [15:0] $end
    $var wire 16 2 mult_pipe[0] [15:0] $end
    $var wire 16 3 mult_pipe[1] [15:0] $end
    $var wire 16 4 mult_pipe[2] [15:0] $end
    $var wire 1 5 done_pipe[0] $end
    $var wire 1 6 done_pipe[1] $end
    $var wire 1 7 done_pipe[2] $end
    $var wire 32 8 i [31:0] $end
   $upscope $end
  $upscope $end
 $upscope $end
$enddefinitions $end


#0
0"
0#
b0000000000000000 $
b0000000000000000 %
b0000000000000000 &
b00000000000000000000000000000000 '
b00000000000000000000000000000000 (
b00000000000000000000000000000000 )
b00000000000000000000000000000000 *
b00000000000000000000000000000000 +
b0000000000000000 ,
b0000000000000000 -
b0000000000000000 .
b0000000000000000 /
b0000000000000000 0
b0000000000000000 1
b0000000000000000 2
b0000000000000000 3
b0000000000000000 4
05
06
07
b00000000000000000000000000000000 8
b0000000000000000 9
b0000000000000000 :
0;
0<
0=
b000 >
0?
b0000000000000000 @
0A
0B
b00000000000000000000000000010000 C
b00000000000000000000000000000011 D
#1
b00000000000000000000000000000011 8
1;
#2
0;
#3
1;
#4
b0000000000000001 9
b0000000000000010 :
0;
1<
1=
b001 >
1A
#5
1"
b0000000000000011 $
b00000000000000000000000000000001 '
b0000000000000001 ,
b0000000000000010 /
b0000000000000010 2
1;
1?
b0000000000000011 @
#6
0;
0=
0A
#7
0"
b0000000000000011 &
b0000000000000001 -
b0000000000000010 0
b0000000000000010 3
1;
0?
#8
0;
#9
b0000000000000001 .
b0000000000000010 1
b0000000000000010 4
1;
#10
0;
#11
b0000000000000010 %
1;
#12
0;
#13
1;
#14
0;
#15
1;
#16
0;
#17
1;
#18
b0000000000000011 9
b0000000000000100 :
0;
1=
b010 >
1A
#19
1"
b0000000000000000 $
b00000000000000000000000000000001 (
b0000000000000011 ,
b0000000000000100 /
b0000000000001100 2
1;
1?
b0000000000000000 @
#20
0;
0=
0A
#21
0"
b0000000000000000 &
b0000000000000011 -
b0000000000000100 0
b0000000000001100 3
1;
0?
#22
0;
#23
b0000000000000011 .
b0000000000000100 1
b0000000000001100 4
1;
#24
0;
#25
b0000000000001100 %
1;
#26
0;
#27
1;
#28
0;
#29
1;
#30
0;
#31
1;
#32
b0000000000000101 9
b0000000000000110 :
0;
1=
b011 >
1A
#33
1"
b0000000000000011 $
b00000000000000000000000000000001 )
b0000000000000101 ,
b0000000000000110 /
b0000000000011110 2
1;
1?
b0000000000000011 @
#34
0;
0=
0A
#35
0"
b0000000000000011 &
b0000000000000101 -
b0000000000000110 0
b0000000000011110 3
1;
0?
#36
0;
#37
b0000000000000101 .
b0000000000000110 1
b0000000000011110 4
1;
#38
0;
#39
b0000000000011110 %
1;
#40
0;
#41
1;
#42
0;
#43
1;
#44
0;
#45
1;
#46
b0000000000000111 9
b0000000000001000 :
0;
1=
b100 >
b0000000000011110 @
1B
#47
b0000000000011110 &
b00000000000000000000000000000001 *
b0000000000000111 ,
b0000000000001000 /
b0000000000111000 2
15
1;
#48
0;
0=
0B
#49
b0000000000000111 -
b0000000000001000 0
b0000000000111000 3
05
16
1;
#50
0;
#51
b0000000000000111 .
b0000000000001000 1
b0000000000111000 4
06
17
1;
#52
0;
#53
1#
b0000000000111000 %
07
1;
1?
b0000000000111000 @
#54
0;
#55
0#
b0000000000111000 &
1;
0?
