tinyalu_ch3_verilator/sim/cov_annotate/three_cycle.sv
//      // verilator_coverage annotation
        // -----------------------------------------------------------------------------
        // Three-Cycle Multiplier (SystemVerilog Conversion of Ray Salemi's VHDL)
        // Enhanced Version: Parameters, Enums, Modern SV, Verilator-Friendly
        // PIPE_DEPTH = 3 by default (P1)
        // -----------------------------------------------------------------------------
        
        module three_cycle #(
            parameter WIDTH         = 16,
            parameter RESULT_WIDTH  = 16,
            parameter PIPE_DEPTH    = 3     // M3: parameterized pipeline depth
        ) (
 000056     input  logic [WIDTH-1:0]        A,
 000056     input  logic [WIDTH-1:0]        B,
 000436     input  logic                    clk,
%000001     input  logic                    reset_n,   // R1: active-low async reset
 000040     input  logic                    start,
 000040     output logic                    done_mult,
 000060     output logic [RESULT_WIDTH-1:0] result_mult
        );
        
            // -------------------------------------------------------------------------
            // Pipeline Registers
            // -------------------------------------------------------------------------
 000056     logic [WIDTH-1:0]        a_pipe   [PIPE_DEPTH];
 000056     logic [WIDTH-1:0]        b_pipe   [PIPE_DEPTH];
 000060     logic [RESULT_WIDTH-1:0] mult_pipe[PIPE_DEPTH];
 000040     logic                    done_pipe[PIPE_DEPTH];
        
            // -------------------------------------------------------------------------
            // Pipeline Logic
            // -------------------------------------------------------------------------
            integer i;
        
 000436     always_ff @(posedge clk or negedge reset_n) begin
~000431         if (!reset_n) begin
~000015             for (i = 0; i < PIPE_DEPTH; i++) begin
 000015                 a_pipe[i]    <= '0;
 000015                 b_pipe[i]    <= '0;
 000015                 mult_pipe[i] <= '0;
 000015                 done_pipe[i] <= 1'b0;
                    end
%000005             result_mult <= '0;
%000005             done_mult   <= 1'b0;
 000431         end else begin
                    // Stage 0: capture inputs
 000431             a_pipe[0]    <= A;
 000431             b_pipe[0]    <= B;
 000431             mult_pipe[0] <= A * B;
 000431             done_pipe[0] <= start;
        
                    // Remaining pipeline stages
 000862             for (i = 1; i < PIPE_DEPTH; i++) begin
 000862                 a_pipe[i]    <= a_pipe[i-1];
 000862                 b_pipe[i]    <= b_pipe[i-1];
 000862                 mult_pipe[i] <= mult_pipe[i-1];
 000862                 done_pipe[i] <= done_pipe[i-1];
                    end
        
                    // Final stage output
 000431             result_mult <= mult_pipe[PIPE_DEPTH-1];
 000431             done_mult   <= done_pipe[PIPE_DEPTH-1];
                end
            end
        
        endmodule

tinyalu_ch3_verilator/sim/cov_annotate/single_cycle.sv
//      // verilator_coverage annotation
        // -----------------------------------------------------------------------------
        // Single-Cycle Add/AND/XOR (SystemVerilog Conversion of Ray Salemi's VHDL)
        // Enhanced Version: Parameters, Enums, Modern SV, Verilator-Friendly
        // -----------------------------------------------------------------------------
        
        module single_cycle #(
            parameter WIDTH         = 16,
            parameter RESULT_WIDTH  = 16
        ) (
 000056     input  logic [WIDTH-1:0]        A,
 000056     input  logic [WIDTH-1:0]        B,
 000436     input  logic                    clk,
%000001     input  logic                    reset_n,   // R1: active-low async reset
 000065     input  logic                    start,
 000055     input  tinyalu_op_t             op,        // O2: enum opcodes
 000053     output logic                    done_aax,
 000034     output logic [RESULT_WIDTH-1:0] result_aax
        );
        
            // -------------------------------------------------------------------------
            // Result Logic
            // -------------------------------------------------------------------------
 000436     always_ff @(posedge clk or negedge reset_n) begin
~000431         if (!reset_n) begin
%000005             result_aax <= '0;
 000271         end else if (start) begin
 000160             case (op)
 000050                 OP_ADD: result_aax <= A + B;
 000034                 OP_AND: result_aax <= { {(RESULT_WIDTH-WIDTH){1'b0}}, (A & B) };
 000039                 OP_XOR: result_aax <= { {(RESULT_WIDTH-WIDTH){1'b0}}, (A ^ B) };
 000037                 default: /* no-op */ ;
                    endcase
                end
            end
        
            // -------------------------------------------------------------------------
            // Done Logic
            // -------------------------------------------------------------------------
 000436     always_ff @(posedge clk or negedge reset_n) begin
~000431         if (!reset_n) begin
%000005             done_aax <= 1'b0;
 000431         end else begin
 000431             done_aax <= (start && (op != OP_NOP));
                end
            end
        
        endmodule

tinyalu_ch3_verilator/sim/cov_annotate/tinyalu.sv
//      // verilator_coverage annotation
        // -----------------------------------------------------------------------------
        // TinyALU Top-Level (SystemVerilog Conversion of Ray Salemi's VHDL)
        // Enhanced Version: Parameters, Enums, Modern SV, Verilator-Friendly
        // -----------------------------------------------------------------------------
        
        module tinyalu #(
            parameter WIDTH         = 16,
            parameter RESULT_WIDTH  = 16,
            parameter PIPE_DEPTH    = 3     // M3: parameterized pipeline depth (default 3)
        ) (
 000056     input  logic [WIDTH-1:0]        A,
 000056     input  logic [WIDTH-1:0]        B,
 000436     input  logic                    clk,
%000001     input  logic                    reset_n,   // R1: active-low async reset
 000078     input  logic                    start,
 000055     input  tinyalu_op_t             op,        // O2: enum opcodes
 000093     output logic                    done,
 000098     output logic [RESULT_WIDTH-1:0] result
        );
        
            // -------------------------------------------------------------------------
            // Internal signals
            // -------------------------------------------------------------------------
 000065     logic                    start_single;
 000040     logic                    start_mult;
        
 000053     logic                    done_aax;
 000040     logic                    done_mult;
        
 000034     logic [RESULT_WIDTH-1:0] result_aax;
 000060     logic [RESULT_WIDTH-1:0] result_mult;
 000063     logic [RESULT_WIDTH-1:0] prev_result;
            // Functional coverage counters     
            integer cov_add, cov_and, cov_xor, cov_mul,cov_nop;
        
 000436     always_ff @(posedge clk or negedge reset_n) 
 000436         begin
~000431             if (!reset_n) 
%000005                 begin
%000005                     cov_add <= 0;
%000005                     cov_and <= 0;
%000005                     cov_xor <= 0;
%000005                     cov_mul <= 0;
%000005                     cov_nop <= 0;
                        end 
 000231             else if (start)     
 000200                 begin
 000200                     case (op)
 000050                         OP_ADD:  cov_add <= cov_add + 1;
 000034                         OP_AND:  cov_and <= cov_and + 1;
 000039                         OP_XOR:  cov_xor <= cov_xor + 1;
 000040                         OP_MUL:  cov_mul <= cov_mul + 1;
 000037                         default: cov_nop <= cov_nop + 1;
                                    
                            endcase
                        end
                end
        
            // -------------------------------------------------------------------------
            // Start Demux: route start to correct block based on op
            // -------------------------------------------------------------------------
 000249     always_comb begin
 000169         if (op == OP_MUL) begin
 000080             start_single = 1'b0;
 000080             start_mult   = start;
 000169         end else begin
 000169             start_single = start;
 000169             start_mult   = 1'b0;
                end
            end
        
            // -------------------------------------------------------------------------
            // Result Mux
            // -------------------------------------------------------------------------
 000594     always_comb 
 000594         begin
 000594             result = '0;
        
 000594             case (op)
 000187                 OP_NOP:  result = prev_result;       // no-op
 000089                 OP_ADD:  result = result_aax;
 000060                 OP_AND:  result = result_aax;
 000067                 OP_XOR:  result = result_aax;
 000191                 OP_MUL:  result = result_mult;
%000000                 default: result = prev_result;
                    endcase
                end
        
            // -------------------------------------------------------------------------
            // Done Mux
            // -------------------------------------------------------------------------
 000594     always_comb 
 000594         begin
 000594             done = 1'b0;
        
 000594             case (op)
 000187                 OP_NOP:  done = 1'b0;
 000089                 OP_ADD:  done = done_aax;
 000060                 OP_AND:  done = done_aax;
 000067                 OP_XOR:  done = done_aax;
 000191                 OP_MUL:  done = done_mult;
%000000                 default: done = 1'b0;
                    endcase
                end
        
            
            
        
 000436     always_ff @(posedge clk or negedge reset_n)
~000431         if (!reset_n)
%000005             prev_result <= '0;
                else
 000431             prev_result <= result;
        
            // -------------------------------------------------------------------------
            // Instantiations
            // -------------------------------------------------------------------------
            single_cycle #(
                .WIDTH(WIDTH),
                .RESULT_WIDTH(RESULT_WIDTH)
            ) u_single_cycle (
                .A(A),
                .B(B),
                .clk(clk),
                .reset_n(reset_n),
                .start(start_single),
                .op(op),
                .done_aax(done_aax),
                .result_aax(result_aax)
            );
        
            three_cycle #(
                .WIDTH(WIDTH),
                .RESULT_WIDTH(RESULT_WIDTH),
                .PIPE_DEPTH(PIPE_DEPTH)
            ) u_three_cycle (
                .A(A),
                .B(B),
                .clk(clk),
                .reset_n(reset_n),
                .start(start_mult),
                .done_mult(done_mult),
                .result_mult(result_mult)
            );
        
        endmodule

tinyalu_ch3_verilator/sim/tinyalu.vcd
$version Generated by VerilatedVcd $end
$timescale 1ps $end
 $scope module TOP $end
  $var wire 16 9 A [15:0] $end
  $var wire 16 : B [15:0] $end
  $var wire 1 ; clk $end
  $var wire 1 < reset_n $end
  $var wire 1 = start $end
  $var wire 3 > op [2:0] $end
  $var wire 1 ? done $end
  $var wire 16 @ result [15:0] $end
  $scope module tinyalu $end
   $var wire 32 C WIDTH [31:0] $end
   $var wire 32 C RESULT_WIDTH [31:0] $end
   $var wire 32 D PIPE_DEPTH [31:0] $end
   $var wire 16 9 A [15:0] $end
   $var wire 16 : B [15:0] $end
   $var wire 1 ; clk $end
   $var wire 1 < reset_n $end
   $var wire 1 = start $end
   $var wire 3 > op [2:0] $end
   $var wire 1 ? done $end
   $var wire 16 @ result [15:0] $end
   $var wire 1 A start_single $end
   $var wire 1 B start_mult $end
   $var wire 1 " done_aax $end
   $var wire 1 # done_mult $end
   $var wire 16 $ result_aax [15:0] $end
   $var wire 16 % result_mult [15:0] $end
   $var wire 16 & prev_result [15:0] $end
   $var wire 32 ' cov_add [31:0] $end
   $var wire 32 ( cov_and [31:0] $end
   $var wire 32 ) cov_xor [31:0] $end
   $var wire 32 * cov_mul [31:0] $end
   $var wire 32 + cov_nop [31:0] $end
   $scope module u_single_cycle $end
    $var wire 32 C WIDTH [31:0] $end
    $var wire 32 C RESULT_WIDTH [31:0] $end
    $var wire 16 9 A [15:0] $end
    $var wire 16 : B [15:0] $end
    $var wire 1 ; clk $end
    $var wire 1 < reset_n $end
    $var wire 1 A start $end
    $var wire 3 > op [2:0] $end
    $var wire 1 " done_aax $end
    $var wire 16 $ result_aax [15:0] $end
   $upscope $end
   $scope module u_three_cycle $end
    $var wire 32 C WIDTH [31:0] $end
    $var wire 32 C RESULT_WIDTH [31:0] $end
    $var wire 32 D PIPE_DEPTH [31:0] $end
    $var wire 16 9 A [15:0] $end
    $var wire 16 : B [15:0] $end
    $var wire 1 ; clk $end
    $var wire 1 < reset_n $end
    $var wire 1 B start $end
    $var wire 1 # done_mult $end
    $var wire 16 % result_mult [15:0] $end
    $var wire 16 , a_pipe[0] [15:0] $end
    $var wire 16 - a_pipe[1] [15:0] $end
    $var wire 16 . a_pipe[2] [15:0] $end
    $var wire 16 / b_pipe[0] [15:0] $end
    $var wire 16 0 b_pipe[1] [15:0] $end
    $var wire 16 1 b_pipe[2] [15:0] $end
    $var wire 16 2 mult_pipe[0] [15:0] $end
    $var wire 16 3 mult_pipe[1] [15:0] $end
    $var wire 16 4 mult_pipe[2] [15:0] $end
    $var wire 1 5 done_pipe[0] $end
    $var wire 1 6 done_pipe[1] $end
    $var wire 1 7 done_pipe[2] $end
    $var wire 32 8 i [31:0] $end
   $upscope $end
  $upscope $end
 $upscope $end
$enddefinitions $end


#0
0"
0#
b0000000000000000 $
b0000000000000000 %
b0000000000000000 &
b00000000000000000000000000000000 '
b00000000000000000000000000000000 (
b00000000000000000000000000000000 )
b00000000000000000000000000000000 *
b00000000000000000000000000000000 +
b0000000000000000 ,
b0000000000000000 -
b0000000000000000 .
b0000000000000000 /
b0000000000000000 0
b0000000000000000 1
b0000000000000000 2
b0000000000000000 3
b0000000000000000 4
05
06
07
b00000000000000000000000000000011 8
b0000000000000000 9
b0000000000000000 :
1;
0<
0=
b000 >
0?
b0000000000000000 @
0A
0B
b00000000000000000000000000010000 C
b00000000000000000000000000000011 D
#5
1"
b1101011010000111 $
b00000000000000000000000000000001 '
b1011010100000101 ,
b0010000110000010 /
b1001000110001010 2
b1011010100000101 9
b0010000110000010 :
1<
1=
b001 >
1?
b1101011010000111 @
1A
#6
0"
b00000000000000000000000000000001 +
b1100111101100000 ,
b1011010100000101 -
b0001111000100000 /
b0010000110000010 0
b0010110000000000 2
b1001000110001010 3
b1100111101100000 9
b0001111000100000 :
b000 >
0?
b0000000000000000 @
#7
b1100111101100000 -
b1011010100000101 .
b0001111000100000 0
b0010000110000010 1
b0010110000000000 3
b1001000110001010 4
0=
0A
#8
b1001000110001010 %
b1100111101100000 .
b0001111000100000 1
b0010110000000000 4
#9
b0010110000000000 %
#10
b00000000000000000000000000000010 +
b1001000001001111 ,
b1000100110001010 /
b0001000110010110 2
b1001000001001111 9
b1000100110001010 :
1=
1A
#11
b1001000001001111 -
b1000100110001010 0
b0001000110010110 3
0=
0A
#12
b1001000001001111 .
b1000100110001010 1
b0001000110010110 4
#13
b0001000110010110 %
#14
b00000000000000000000000000000011 +
b0101100101110110 ,
b1010001001000010 /
b1011110001101100 2
b0101100101110110 9
b1010001001000010 :
1=
1A
#15
b0101100101110110 -
b1010001001000010 0
b1011110001101100 3
0=
0A
#16
b0101100101110110 .
b1010001001000010 1
b1011110001101100 4
#17
b1011110001101100 %
#18
1"
b0101110001100010 $
b1101011010000111 &
b00000000000000000000000000000010 '
b1001001011011100 ,
b1100100110000110 /
b1001101100101000 2
b1001001011011100 9
b1100100110000110 :
1=
b001 >
1?
b0101110001100010 @
1A
#19
0"
b1011110001101100 &
b00000000000000000000000000000001 *
b0101101100110101 ,
b1001001011011100 -
b0110010011100111 /
b1100100110000110 0
b0000000011010011 2
b1001101100101000 3
15
b0101101100110101 9
b0110010011100111 :
b100 >
0?
b1011110001101100 @
0A
1B
#20
b0101101100110101 -
b1001001011011100 .
b0110010011100111 0
b1100100110000110 1
b0000000011010011 3
b1001101100101000 4
05
16
0=
0B
#21
b1001101100101000 %
b0101101100110101 .
b0110010011100111 1
b0000000011010011 4
06
17
b1001101100101000 @
#22
1#
b0000000011010011 %
b1001101100101000 &
07
1?
b0000000011010011 @
#23
1"
0#
b1101110001111100 $
b0101110001100010 &
b00000000000000000000000000000001 )
b1001010111000000 ,
b0100100110111100 /
b1011100100000000 2
b1001010111000000 9
b0100100110111100 :
1=
b011 >
b1101110001111100 @
1A
#24
b1000010100110001 $
b1101110001111100 &
b00000000000000000000000000000001 (
b1100010100110001 ,
b1001010111000000 -
b1010010101111111 /
b0100100110111100 0
b0110100001001111 2
b1011100100000000 3
b1100010100110001 9
b1010010101111111 :
b010 >
b1000010100110001 @
#25
0"
b0000000011010011 &
b00000000000000000000000000000010 *
b0010001001101000 ,
b1100010100110001 -
b1001010111000000 .
b0001001010111101 /
b1010010101111111 0
b0100100110111100 1
b1011011011001000 2
b0110100001001111 3
b1011100100000000 4
15
b0010001001101000 9
b0001001010111101 :
b100 >
0?
b0000000011010011 @
0A
1B
#26
b1011100100000000 %
b0010001001101000 -
b1100010100110001 .
b0001001010111101 0
b1010010101111111 1
b1011011011001000 3
b0110100001001111 4
05
16
0=
b1011100100000000 @
0B
#27
b0110100001001111 %
b1011100100000000 &
b0010001001101000 .
b0001001010111101 1
b1011011011001000 4
06
17
b0110100001001111 @
#28
1#
b1011011011001000 %
b0110100001001111 &
07
1?
b1011011011001000 @
#29
1"
0#
b0101111001000011 $
b1000010100110001 &
b00000000000000000000000000000010 )
b0001010011111000 ,
b0100101010111011 /
b0000000100101000 2
b0001010011111000 9
b0100101010111011 :
1=
b011 >
b0101111001000011 @
1A
#30
b1000100110100010 $
b0101111001000011 &
b00000000000000000000000000000011 '
b1000100111100010 ,
b0001010011111000 -
b1111111111000000 /
b0100101010111011 0
b1000011110000000 2
b0000000100101000 3
b1000100111100010 9
b1111111111000000 :
b001 >
b1000100110100010 @
#31
0"
b00000000000000000000000000000100 +
b0000010000000111 ,
b1000100111100010 -
b0001010011111000 .
b1100111100100000 /
b1111111111000000 0
b0100101010111011 1
b0010100111100000 2
b1000011110000000 3
b0000000100101000 4
b0000010000000111 9
b1100111100100000 :
b000 >
0?
b0101111001000011 @
#32
b0000000100101000 %
b0000010000000111 -
b1000100111100010 .
b1100111100100000 0
b1111111111000000 1
b0010100111100000 3
b1000011110000000 4
0=
0A
#33
b1000011110000000 %
b0000010000000111 .
b1100111100100000 1
b0010100111100000 4
#34
b0010100111100000 %
#35
1"
b1100110101010101 $
b1000100110100010 &
b00000000000000000000000000000100 '
b0110110111100110 ,
b0101111101101111 /
b0000000010111010 2
b0110110111100110 9
b0101111101101111 :
1=
b001 >
1?
b1100110101010101 @
1A
#36
0"
b0010100111100000 &
b00000000000000000000000000000011 *
b1101001000011000 ,
b0110110111100110 -
b1011100011100101 /
b0101111101101111 0
b0010111101111000 2
b0000000010111010 3
15
b1101001000011000 9
b1011100011100101 :
b100 >
0?
b0010100111100000 @
0A
1B
#37
b1101001000011000 -
b0110110111100110 .
b1011100011100101 0
b0101111101101111 1
b0010111101111000 3
b0000000010111010 4
05
16
0=
0B
#38
b0000000010111010 %
b1101001000011000 .
b1011100011100101 1
b0010111101111000 4
06
17
b0000000010111010 @
#39
1#
b0010111101111000 %
b0000000010111010 &
07
1?
b0010111101111000 @
#40
0#
b0010111101111000 &
b00000000000000000000000000000100 *
b1101110011110100 ,
b0100101111000010 /
b1110110011101000 2
15
b1101110011110100 9
b0100101111000010 :
1=
0?
1B
#41
b1101110011110100 -
b0100101111000010 0
b1110110011101000 3
05
16
0=
0B
#42
b1101110011110100 .
b0100101111000010 1
b1110110011101000 4
06
17
#43
1#
b1110110011101000 %
07
1?
b1110110011101000 @
#44
1"
0#
b1000100111101001 $
b1100110101010101 &
b00000000000000000000000000000101 '
b1110001011110010 ,
b1010011011110111 /
b1110001101111110 2
b1110001011110010 9
b1010011011110111 :
1=
b001 >
b1000100111101001 @
1A
#45
b0111000110110010 $
b1000100111101001 &
b00000000000000000000000000000110 '
b0011010011111011 ,
b1110001011110010 -
b0011110010110111 /
b1010011011110111 0
b1011001101101101 2
b1110001101111110 3
b0011010011111011 9
b0011110010110111 :
b0111000110110010 @
#46
0"
b1110110011101000 &
b00000000000000000000000000000101 *
b0001010010111110 ,
b0011010011111011 -
b1110001011110010 .
b0000000111101001 /
b0011110010110111 0
b1010011011110111 1
b1001111011101110 2
b1011001101101101 3
b1110001101111110 4
15
b0001010010111110 9
b0000000111101001 :
b100 >
0?
b1110110011101000 @
0A
1B
#47
b1110001101111110 %
b0001010010111110 -
b0011010011111011 .
b0000000111101001 0
b0011110010110111 1
b1001111011101110 3
b1011001101101101 4
05
16
0=
b1110001101111110 @
0B
#48
b1011001101101101 %
b1110001101111110 &
b0001010010111110 .
b0000000111101001 1
b1001111011101110 4
06
17
b1011001101101101 @
#49
1#
b1001111011101110 %
b1011001101101101 &
07
1?
b1001111011101110 @
#50
0#
b1001111011101110 &
b00000000000000000000000000000110 *
b0101100001011110 ,
b0010010001010001 /
b0010110110111110 2
15
b0101100001011110 9
b0010010001010001 :
1=
0?
1B
#51
b0101100001011110 -
b0010010001010001 0
b0010110110111110 3
05
16
0=
0B
#52
b0101100001011110 .
b0010010001010001 1
b0010110110111110 4
06
17
#53
1#
b0010110110111110 %
07
1?
b0010110110111110 @
#54
1"
0#
b1001101110011101 $
b0111000110110010 &
b00000000000000000000000000000011 )
b1010001011010100 ,
b0011100101001001 /
b1010001001110100 2
b1010001011010100 9
b0011100101001001 :
1=
b011 >
b1001101110011101 @
1A
#55
b1110101111111011 $
b1001101110011101 &
b00000000000000000000000000000100 )
b0010100011010111 ,
b1010001011010100 -
b1100001100101100 /
b0011100101001001 0
b1100100111110100 2
b1010001001110100 3
b0010100011010111 9
b1100001100101100 :
b1110101111111011 @
#56
b0001011101101111 $
b1110101111111011 &
b00000000000000000000000000000101 )
b1101000001011100 ,
b0010100011010111 -
b1010001011010100 .
b1100011100110011 /
b1100001100101100 0
b0011100101001001 1
b0000011001010100 2
b1100100111110100 3
b1010001001110100 4
b1101000001011100 9
b1100011100110011 :
b0001011101101111 @
#57
0"
b1010001001110100 %
b0010110110111110 &
b00000000000000000000000000000111 *
b1001011000000001 ,
b1101000001011100 -
b0010100011010111 .
b0011010100011001 /
b1100011100110011 0
b1100001100101100 1
b1101101100011001 2
b0000011001010100 3
b1100100111110100 4
15
b1001011000000001 9
b0011010100011001 :
b100 >
0?
b1010001001110100 @
0A
1B
#58
b1100100111110100 %
b1010001001110100 &
b1001011000000001 -
b1101000001011100 .
b0011010100011001 0
b1100011100110011 1
b1101101100011001 3
b0000011001010100 4
05
16
0=
b1100100111110100 @
0B
#59
b0000011001010100 %
b1100100111110100 &
b1001011000000001 .
b0011010100011001 1
b1101101100011001 4
06
17
b0000011001010100 @
#60
1#
b1101101100011001 %
b0000011001010100 &
07
1?
b1101101100011001 @
#61
0#
b00000000000000000000000000000101 +
b1110010100110001 ,
b0000011100110010 /
b0001101010010010 2
b1110010100110001 9
b0000011100110010 :
1=
b000 >
0?
b0000011001010100 @
1A
#62
b1110010100110001 -
b0000011100110010 0
b0001101010010010 3
0=
0A
#63
b1110010100110001 .
b0000011100110010 1
b0001101010010010 4
#64
b0001101010010010 %
#65
1"
b1011101011001000 $
b0001011101101111 &
b00000000000000000000000000000111 '
b1101011010100010 ,
b1110010000100110 /
b0010010000001100 2
b1101011010100010 9
b1110010000100110 :
1=
b001 >
1?
b1011101011001000 @
1A
#66
b0101011010000010 $
b1011101011001000 &
b00000000000000000000000000000110 )
b1001000110011010 ,
b1101011010100010 -
b1100011100011000 /
b1110010000100110 0
b0101110001110000 2
b0010010000001100 3
b1001000110011010 9
b1100011100011000 :
b011 >
b0101011010000010 @
#67
b0100110101101010 $
b0101011010000010 &
b00000000000000000000000000000111 )
b1011000101111001 ,
b1001000110011010 -
b1101011010100010 .
b1111110000010011 /
b1100011100011000 0
b1110010000100110 1
b0100011111111011 2
b0101110001110000 3
b0010010000001100 4
b1011000101111001 9
b1111110000010011 :
b0100110101101010 @
#68
b0000101111000101 $
b0010010000001100 %
b0100110101101010 &
b00000000000000000000000000001000 )
b0001101100010100 ,
b1011000101111001 -
b1001000110011010 .
b0001000011010001 /
b1111110000010011 0
b1100011100011000 1
b0101101101010100 2
b0100011111111011 3
b0101110001110000 4
b0001101100010100 9
b0001000011010001 :
b0000101111000101 @
#69
0"
b0101110001110000 %
b0010010000001100 &
b00000000000000000000000000001000 *
b0010101000101111 ,
b0001101100010100 -
b1011000101111001 .
b0110100100101111 /
b0001000011010001 0
b1111110000010011 1
b0000010110100001 2
b0101101101010100 3
b0100011111111011 4
15
b0010101000101111 9
b0110100100101111 :
b100 >
0?
b0101110001110000 @
0A
1B
#70
b0100011111111011 %
b0101110001110000 &
b0010101000101111 -
b0001101100010100 .
b0110100100101111 0
b0001000011010001 1
b0000010110100001 3
b0101101101010100 4
05
16
0=
b0100011111111011 @
0B
#71
b0101101101010100 %
b0100011111111011 &
b0010101000101111 .
b0110100100101111 1
b0000010110100001 4
06
17
b0101101101010100 @
#72
1#
b0000010110100001 %
b0101101101010100 &
07
1?
b0000010110100001 @
#73
1"
0#
b0000110000000011 $
b0000101111000101 &
b00000000000000000000000000000010 (
b0100110000000111 ,
b0000110000000011 /
b0011100000010101 2
b0100110000000111 9
b0000110000000011 :
1=
b010 >
b0000110000000011 @
1A
#74
0"
b0000010110100001 &
b00000000000000000000000000001001 *
b1011100010011010 ,
b0100110000000111 -
b0011010011011010 /
b0000110000000011 0
b0111101100100100 2
b0011100000010101 3
15
b1011100010011010 9
b0011010011011010 :
b100 >
0?
b0000010110100001 @
0A
1B
#75
b1011100010011010 -
b0100110000000111 .
b0011010011011010 0
b0000110000000011 1
b0111101100100100 3
b0011100000010101 4
05
16
0=
0B
#76
b0011100000010101 %
b1011100010011010 .
b0011010011011010 1
b0111101100100100 4
06
17
b0011100000010101 @
#77
1#
b0111101100100100 %
b0011100000010101 &
07
1?
b0111101100100100 @
#78
0#
b0111101100100100 &
b00000000000000000000000000001010 *
b0010010011101101 ,
b0000010100110110 /
b0110101011111110 2
15
b0010010011101101 9
b0000010100110110 :
1=
0?
1B
#79
b0010010011101101 -
b0000010100110110 0
b0110101011111110 3
05
16
0=
0B
#80
b0010010011101101 .
b0000010100110110 1
b0110101011111110 4
06
17
#81
1#
b0110101011111110 %
07
1?
b0110101011111110 @
#82
1"
0#
b1111101110011000 $
b0000110000000011 &
b00000000000000000000000000001000 '
b0110000001100000 ,
b1001101100111000 /
b0011010100000000 2
b0110000001100000 9
b1001101100111000 :
1=
b001 >
b1111101110011000 @
1A
#83
b0111101110101100 $
b1111101110011000 &
b00000000000000000000000000001001 '
b1111101101000011 ,
b0110000001100000 -
b1000000001101001 /
b1001101100111000 0
b1000111001111011 2
b0011010100000000 3
b1111101101000011 9
b1000000001101001 :
b0111101110101100 @
#84
b0100011100001000 $
b0111101110101100 &
b00000000000000000000000000000011 (
b0100111100001100 ,
b1111101101000011 -
b0110000001100000 .
b0101011100001011 /
b1000000001101001 0
b1001101100111000 1
b0111100110000100 2
b1000111001111011 3
b0011010100000000 4
b0100111100001100 9
b0101011100001011 :
b010 >
b0100011100001000 @
#85
b0000011000110011 $
b0011010100000000 %
b0100011100001000 &
b00000000000000000000000000001001 )
b1110111010010110 ,
b0100111100001100 -
b1111101101000011 .
b1110100010100101 /
b0101011100001011 0
b1000000001101001 1
b1011011010101110 2
b0111100110000100 3
b1000111001111011 4
b1110111010010110 9
b1110100010100101 :
b011 >
b0000011000110011 @
#86
0"
b1000111001111011 %
b00000000000000000000000000000110 +
b0011010100011000 ,
b1110111010010110 -
b0100111100001100 .
b1001101000011110 /
b1110100010100101 0
b0101011100001011 1
b1010100011010000 2
b1011011010101110 3
b0111100110000100 4
b0011010100011000 9
b1001101000011110 :
b000 >
0?
b0100011100001000 @
#87
b0111100110000100 %
b0011010100011000 -
b1110111010010110 .
b1001101000011110 0
b1110100010100101 1
b1010100011010000 3
b1011011010101110 4
0=
0A
#88
b1011011010101110 %
b0011010100011000 .
b1001101000011110 1
b1010100011010000 4
#89
b1010100011010000 %
#90
1"
b0110110110000101 $
b0000011000110011 &
b00000000000000000000000000001010 '
b1011100001010010 ,
b1011010100110011 /
b1011001001010110 2
b1011100001010010 9
b1011010100110011 :
1=
b001 >
1?
b0110110110000101 @
1A
#91
b0001110101100000 $
b0110110110000101 &
b00000000000000000000000000000100 (
b0011110101110100 ,
b1011100001010010 -
b1101111101100010 /
b1011010100110011 0
b1001001001101000 2
b1011001001010110 3
b0011110101110100 9
b1101111101100010 :
b010 >
b0001110101100000 @
#92
0"
b00000000000000000000000000000111 +
b1110011011101000 ,
b0011110101110100 -
b1011100001010010 .
b0010101101101001 /
b1101111101100010 0
b1011010100110011 1
b1010110100101000 2
b1001001001101000 3
b1011001001010110 4
b1110011011101000 9
b0010101101101001 :
b000 >
0?
b0110110110000101 @
#93
b1011001001010110 %
b1110011011101000 -
b0011110101110100 .
b0010101101101001 0
b1101111101100010 1
b1010110100101000 3
b1001001001101000 4
0=
0A
#94
b1001001001101000 %
b1110011011101000 .
b0010101101101001 1
b1010110100101000 4
#95
b1010110100101000 %
#96
b00000000000000000000000000001000 +
b1100100110100101 ,
b1110010000000011 /
b0101000011101111 2
b1100100110100101 9
b1110010000000011 :
1=
1A
#97
b1100100110100101 -
b1110010000000011 0
b0101000011101111 3
0=
0A
#98
b1100100110100101 .
b1110010000000011 1
b0101000011101111 4
#99
b0101000011101111 %
#100
1"
b0110011101111110 $
b0001110101100000 &
b00000000000000000000000000001010 )
b0110111110001110 ,
b0000100011110000 /
b0000010100100000 2
b0110111110001110 9
b0000100011110000 :
1=
b011 >
1?
b0110011101111110 @
1A
#101
b0100010111111010 $
b0110011101111110 &
b00000000000000000000000000001011 '
b1101110010101010 ,
b0110111110001110 -
b0110100101010000 /
b0000100011110000 0
b1010111100100000 2
b0000010100100000 3
b1101110010101010 9
b0110100101010000 :
b001 >
b0100010111111010 @
#102
0"
b0101000011101111 &
b00000000000000000000000000001011 *
b0111111011100000 ,
b1101110010101010 -
b0110111110001110 .
b0110010010010100 /
b0110100101010000 0
b0000100011110000 1
b1101100110000000 2
b1010111100100000 3
b0000010100100000 4
15
b0111111011100000 9
b0110010010010100 :
b100 >
0?
b0101000011101111 @
0A
1B
#103
b0000010100100000 %
b0111111011100000 -
b1101110010101010 .
b0110010010010100 0
b0110100101010000 1
b1101100110000000 3
b1010111100100000 4
05
16
0=
b0000010100100000 @
0B
#104
b1010111100100000 %
b0000010100100000 &
b0111111011100000 .
b0110010010010100 1
b1101100110000000 4
06
17
b1010111100100000 @
#105
1#
b1101100110000000 %
b1010111100100000 &
07
1?
b1101100110000000 @
#106
1"
0#
b1001101111101000 $
b0100010111111010 &
b00000000000000000000000000001011 )
b0010100001001000 ,
b1011001110100000 /
b1000010100000000 2
b0010100001001000 9
b1011001110100000 :
1=
b011 >
b1001101111101000 @
1A
#107
b1010000000010110 $
b1001101111101000 &
b00000000000000000000000000000101 (
b1011010111010110 ,
b0010100001001000 -
b1010001000110110 /
b1011001110100000 0
b1100011100100100 2
b1000010100000000 3
b1011010111010110 9
b1010001000110110 :
b010 >
b1010000000010110 @
#108
0"
b1101100110000000 &
b00000000000000000000000000001100 *
b0000101001111100 ,
b1011010111010110 -
b0010100001001000 .
b1101011101001111 /
b1010001000110110 0
b1011001110100000 1
b0110000001000100 2
b1100011100100100 3
b1000010100000000 4
15
b0000101001111100 9
b1101011101001111 :
b100 >
0?
b1101100110000000 @
0A
1B
#109
b1000010100000000 %
b0000101001111100 -
b1011010111010110 .
b1101011101001111 0
b1010001000110110 1
b0110000001000100 3
b1100011100100100 4
05
16
0=
b1000010100000000 @
0B
#110
b1100011100100100 %
b1000010100000000 &
b0000101001111100 .
b1101011101001111 1
b0110000001000100 4
06
17
b1100011100100100 @
#111
1#
b0110000001000100 %
b1100011100100100 &
07
1?
b0110000001000100 @
#112
1"
0#
b0000101100100001 $
b1010000000010110 &
b00000000000000000000000000000110 (
b0101101100110101 ,
b1000111110100001 /
b1111011101010101 2
b0101101100110101 9
b1000111110100001 :
1=
b010 >
b0000101100100001 @
1A
